Workbook

Sheet Dashboard
B2: LOCALHOST
B3: Monthly data sheet · v1.0 · fill, save, upload
B5: APARTMENT NAME | E5: MONTH | H5: PREPARED BY
B8: REGISTRATION ID | E8: SUBMISSION DATE | H8: CONTACT (PHONE / EMAIL)
B11: MEMBER ROSTER
B12: EMAIL is how the system identifies each member. Use the exact email already registered in the app. The order here defines Member 1, Member 2 … used in the Meals tab.
B13: # | C13: FULL NAME | D13: EMAIL (identifier) | E13: STATUS | F13: ROLE | G13: PHONE | H13: NOTES
B14: 01
B15: 02
B16: 03
B17: 04
B18: 05
B19: 06
B20: 07
B21: 08
B23: FIXED COSTS | E23: OTHER EXPENSES | G23: MARKET TOTAL | I23: TOTAL MEALS
B24: ='Costs'!C47 | E24: ='Costs'!F88 | G24: ='Costs'!E31 | I24: ='Meals'!K77
B25: auto-calculated · live | E25: auto-calculated · live | G25: auto-calculated · live | I25: auto-calculated · live
B27: Need help? Fill the Roster first, then Meals, then Costs. Cells in white are editable.

Sheet Meals
B2: MEALS
B3: One sheet per meal slot · 2 slots
B5: LUNCH
B6: Enter meal count per member per day (e.g. 1, 1.5 with guest, 0 if skipped).
B7: DAY | C7: ="M01 — " & IF('Dashboard'!C14="","(empty)",'Dashboard'!C14) | D7: ="M02 — " & IF('Dashboard'!C15="","(empty)",'Dashboard'!C15) | E7: ="M03 — " & IF('Dashboard'!C16="","(empty)",'Dashboard'!C16) | F7: ="M04 — " & IF('Dashboard'!C17="","(empty)",'Dashboard'!C17) | G7: ="M05 — " & IF('Dashboard'!C18="","(empty)",'Dashboard'!C18) | H7: ="M06 — " & IF('Dashboard'!C19="","(empty)",'Dashboard'!C19) | I7: ="M07 — " & IF('Dashboard'!C20="","(empty)",'Dashboard'!C20) | J7: ="M08 — " & IF('Dashboard'!C21="","(empty)",'Dashboard'!C21) | K7: DAY TOTAL
B8: 01 | K8: =IFERROR(SUM(C8:J8),0)
B9: 02 | K9: =IFERROR(SUM(C9:J9),0)
B10: 03 | K10: =IFERROR(SUM(C10:J10),0)
B11: 04 | K11: =IFERROR(SUM(C11:J11),0)
B12: 05 | K12: =IFERROR(SUM(C12:J12),0)
B13: 06 | K13: =IFERROR(SUM(C13:J13),0)
B14: 07 | K14: =IFERROR(SUM(C14:J14),0)
B15: 08 | K15: =IFERROR(SUM(C15:J15),0)
B16: 09 | K16: =IFERROR(SUM(C16:J16),0)
B17: 10 | K17: =IFERROR(SUM(C17:J17),0)
B18: 11 | K18: =IFERROR(SUM(C18:J18),0)
B19: 12 | K19: =IFERROR(SUM(C19:J19),0)
... B38: 31 | K38: =IFERROR(SUM(C38:J38),0)
B39: LUNCH TOTAL | C39: =IFERROR(SUM(C8:C38),0) | D39: =IFERROR(SUM(D8:D38),0) | E39: =IFERROR(SUM(E8:E38),0) | F39: =IFERROR(SUM(F8:F38),0) | G39: =IFERROR(SUM(G8:G38),0) | H39: =IFERROR(SUM(H8:H38),0) | I39: =IFERROR(SUM(I8:I38),0) | J39: =IFERROR(SUM(J8:J38),0) | K39: =IFERROR(SUM(K8:K38),0)
B41: DINNER
B42: Enter meal count per member per day (e.g. 1, 1.5 with guest, 0 if skipped).
B43: DAY | C43: ="M01 — " & IF('Dashboard'!C14="","(empty)",'Dashboard'!C14) | D43: ="M02 — " & IF('Dashboard'!C15="","(empty)",'Dashboard'!C15) | E43: ="M03 — " & IF('Dashboard'!C16="","(empty)",'Dashboard'!C16) | F43: ="M04 — " & IF('Dashboard'!C17="","(empty)",'Dashboard'!C17) | G43: ="M05 — " & IF('Dashboard'!C18="","(empty)",'Dashboard'!C18) | H43: ="M06 — " & IF('Dashboard'!C19="","(empty)",'Dashboard'!C19) | I43: ="M07 — " & IF('Dashboard'!C20="","(empty)",'Dashboard'!C20) | J43: ="M08 — " & IF('Dashboard'!C21="","(empty)",'Dashboard'!C21) | K43: DAY TOTAL
B44: 01 | K44: =IFERROR(SUM(C44:J44),0)
B45: 02 | K45: =IFERROR(SUM(C45:J45),0)
B46: 03 | K46: =IFERROR(SUM(C46:J46),0)
B47: 04 | K47: =IFERROR(SUM(C47:J47),0)
B48: 05 | K48: =IFERROR(SUM(C48:J48),0)
B49: 06 | K49: =IFERROR(SUM(C49:J49),0)
B50: 07 | K50: =IFERROR(SUM(C50:J50),0)
B51: 08 | K51: =IFERROR(SUM(C51:J51),0)
B52: 09 | K52: =IFERROR(SUM(C52:J52),0)
B53: 10 | K53: =IFERROR(SUM(C53:J53),0)
B54: 11 | K54: =IFERROR(SUM(C54:J54),0)
B55: 12 | K55: =IFERROR(SUM(C55:J55),0)
... B74: 31 | K74: =IFERROR(SUM(C74:J74),0)
B75: DINNER TOTAL | C75: =IFERROR(SUM(C44:C74),0) | D75: =IFERROR(SUM(D44:D74),0) | E75: =IFERROR(SUM(E44:E74),0) | F75: =IFERROR(SUM(F44:F74),0) | G75: =IFERROR(SUM(G44:G74),0) | H75: =IFERROR(SUM(H44:H74),0) | I75: =IFERROR(SUM(I44:I74),0) | J75: =IFERROR(SUM(J44:J74),0) | K75: =IFERROR(SUM(K44:K74),0)
B77: ALL MEALS — MONTH GRAND TOTAL | K77: =K39+K75

Sheet Costs
B2: COSTS
B3: Market shopping, fixed costs, monthly bill, and other expenses
B5: MEAL MARKET SHOPPING · who bought what for meals
B6: Date | C6: Item | D6: Quantity | E6: Amount | F6: Bought By (Email) | G6: Receipt # | H6: Notes
B31: MARKET TOTAL | E31: =IFERROR(SUM(E7:E30),0)
B33: FIXED COSTS · monthly recurring amounts
B34: Cost Item | C34: Amount | D34: Paid By (Email) | E34: Payment Method | F34: Reference | G34: Due Date | H34: Notes
B47: FIXED TOTAL | C47: =IFERROR(SUM(C35:C46),0)
B49: MONTHLY BILL · meter readings and adjustments
B50: ELECTRICITY READING (units) | E50: ELECTRICITY AMOUNT
B52: Member Email | C52: Type (extra/deduct) | D52: Label | E52: Amount | F52: Created By | G52: Date | H52: Notes
B62: OTHER EXPENSES · one-off and per-member items
B63: Date | C63: Category | D63: Description | E63: Bought By (Email) | F63: Amount | G63: Payment Method | H63: Notes
B88: OTHER EXPENSES TOTAL | F88: =IFERROR(SUM(F64:F87),0)

Sheet Lists
A1: January | B1: Cash | C1: Grocery | D1: Active | E1: Admin | F1: extra
A2: February | B2: Bank Transfer | C2: Utility | D2: Guest | E2: Bill Manager | F2: deduct
A3: March | B3: bKash | C3: Transport | D3: Inactive | E3: Member
A4: April | B4: Nagad | C4: Internet
A5: May | B5: Card | C5: Maintenance
A6: June | B6: Other | C6: Cleaning
A7: July | C7: Medicine
A8: August | C8: Repair
A9: September | C9: Other
A10: October
A11: November
A12: December

Sheet Schema
A1: LocalHost Monthly Template — Schema mapping
A3: Section | B3: Sheet range | C3: Maps to (Prisma model) | D3: Notes
A4: Roster | B4: Dashboard!C14:G21 | C4: Member | D4: Match by email (apartmentId+email is unique)
A5: Meals | B5: Meals!C… | C5: MealRecord | D5: One sheet section per meal slot
A6: Market | B6: Costs!B7:H30 | C6: MealShopping | D6: Per-purchase rows
A7: Fixed costs | B7: Costs!B35:H46 | C7: FixedCost | D7: Monthly recurring items
A8: Bill / adj | B8: Costs!B53:H60 | C8: BillAdjustment / MonthlyBill | D8: Electricity reading + per-member adjustments
A9: Other expenses | B9: Costs!B64:H87 | C9: Expense | D9: Variable monthly expenses
